{
 "meta": {
  "match_id": "m_001",
  "captured_at": "2026-07-06T23:59:13.618233Z",
  "description": "Real YouTube live-chat capture of https://www.youtube.com/watch?v=JyP6Hzt7y84 (331 messages)",
  "video_id": "JyP6Hzt7y84"
 },
 "items": [
  {
   "t_offset": 30.72,
   "external_id": "yt_ChwKGkNPdkoxNWpjdnBVREZmamk1d01kSUxFeldB",
   "source": "youtube",
   "author": "@4anas_____7",
   "text": "hi",
   "country": null
  },
  {
   "t_offset": 56.87,
   "external_id": "yt_ChwKGkNQbjhrcVhjdnBVREZRM1A1d01kYllNYTlB",
   "source": "youtube",
   "author": "@4anas_____7",
   "text": "cr7",
   "country": null
  },
  {
   "t_offset": 62.17,
   "external_id": "yt_ChwKGkNPT2kxS2ZjdnBVREZVWER3Z1FkbzNzNC1B",
   "source": "youtube",
   "author": "@4anas_____7",
   "text": ":hand-pink-waving::face-blue-smiling:",
   "country": null
  },
  {
   "t_offset": 118.74,
   "external_id": "yt_ChwKGkNPMnIxTUxjdnBVREZlb1RyUVlkYlFJakR3",
   "source": "youtube",
   "author": "@4anas_____7",
   "text": "777",
   "country": null
  },
  {
   "t_offset": 122.7,
   "external_id": "yt_ChwKGkNPZXp4TVRjdnBVREZaNUZUQWdkRVg4ZjBn",
   "source": "youtube",
   "author": "@4anas_____7",
   "text": "siuuuu",
   "country": null
  },
  {
   "t_offset": 140.79,
   "external_id": "yt_ChwKGkNKek9sYzNjdnBVREZUVVhkZ1lkZm5jeGVn",
   "source": "youtube",
   "author": "@4anas_____7",
   "text": "say my name",
   "country": null
  },
  {
   "t_offset": 159.29,
   "external_id": "yt_ChwKGkNQUHRfOVhjdnBVREZlTGV3Z1FkZ000ME1n",
   "source": "youtube",
   "author": "@lonelysomeoneytofficial",
   "text": "CR7 ONLY",
   "country": null
  },
  {
   "t_offset": 176.38,
   "external_id": "yt_ChwKGkNQT3VrdDdjdnBVREZlRk9UQWdkX3Bjc2xB",
   "source": "youtube",
   "author": "@4anas_____7",
   "text": "cr7",
   "country": null
  },
  {
   "t_offset": 183.69,
   "external_id": "yt_ChwKGkNOejJ6dUhjdnBVREZlamZ3Z1FkZVRBQmFB",
   "source": "youtube",
   "author": "@lonelysomeoneytofficial",
   "text": "cr7",
   "country": null
  },
  {
   "t_offset": 202.84,
   "external_id": "yt_ChwKGkNKVEszLXJjdnBVREZUbkN3Z1FkS3hJS0N3",
   "source": "youtube",
   "author": "@4anas_____7",
   "text": "your insta id",
   "country": null
  },
  {
   "t_offset": 203.62,
   "external_id": "yt_ChwKGkNJWFZqLXZjdnBVREZUX0N3Z1FkajBzcGlR",
   "source": "youtube",
   "author": "@RannaShaji",
   "text": "ഹി",
   "country": null
  },
  {
   "t_offset": 211.14,
   "external_id": "yt_ChwKGkNMYVYzTzdjdnBVREZlTFN3Z1Fka0VVUjNR",
   "source": "youtube",
   "author": "@lonelysomeoneytofficial",
   "text": "live link in available need any one",
   "country": null
  },
  {
   "t_offset": 237.48,
   "external_id": "yt_ChwKGkNLQ21vX3ZjdnBVREZmeElUQWdkQWNVTE13",
   "source": "youtube",
   "author": "@lonelysomeoneytofficial",
   "text": "itz.mdanjar",
   "country": null
  },
  {
   "t_offset": 244.14,
   "external_id": "yt_ChwKGkNKdWp1UDdjdnBVREZmUFB3Z1FkekJzUHh3",
   "source": "youtube",
   "author": "@4anas_____7",
   "text": "siuuuu",
   "country": null
  },
  {
   "t_offset": 245.72,
   "external_id": "yt_ChwKGkNPS09tZl9jdnBVREZiN0h3Z1FkZVVvS1Fn",
   "source": "youtube",
   "author": "@lonelysomeoneytofficial",
   "text": "insta",
   "country": null
  },
  {
   "t_offset": 277.74,
   "external_id": "yt_ChwKGkNKdmF2WTdkdnBVREZVZ2JkZ1lkdEVJVUh3",
   "source": "youtube",
   "author": "@4anas_____7",
   "text": "4anas_____",
   "country": null
  },
  {
   "t_offset": 284.61,
   "external_id": "yt_ChwKGkNMR0Y0WkhkdnBVREZldzBkZ1lkdV9BTzhB",
   "source": "youtube",
   "author": "@4anas_____7",
   "text": "5times",
   "country": null
  },
  {
   "t_offset": 305.69,
   "external_id": "yt_ChwKGkNQR2I2SnZkdnBVREZlRFo1d01kWlA0cnZn",
   "source": "youtube",
   "author": "@4anas_____7",
   "text": "hlo",
   "country": null
  },
  {
   "t_offset": 311.43,
   "external_id": "yt_ChwKGkNPSzh4SjdkdnBVREZUNThUQWdkbWlzaDFn",
   "source": "youtube",
   "author": "@Gopal_choudhary_9090",
   "text": "bhai kisi ko hindi aati hai yaha ?",
   "country": null
  },
  {
   "t_offset": 369.98,
   "external_id": "yt_ChwKGkNNN2Z1cnJkdnBVREZiY19yUVlkdkt3UTZB",
   "source": "youtube",
   "author": "@amandeepmor07",
   "text": "haa",
   "country": null
  },
  {
   "t_offset": 377.16,
   "external_id": "yt_ChwKGkNLZko4TDNkdnBVREZUelR3Z1FkT2I0c293",
   "source": "youtube",
   "author": "@4anas_____7",
   "text": "cr7",
   "country": null
  },
  {
   "t_offset": 390.81,
   "external_id": "yt_ChwKGkNOLTlzY1RkdnBVREZWZ3FyUVlkaDhVbW93",
   "source": "youtube",
   "author": "@LawraBhai-p6h",
   "text": "good luck cr7",
   "country": null
  },
  {
   "t_offset": 409.55,
   "external_id": "yt_ChwKGkNOSGlxczNkdnBVREZmZkI1d01kN08wd1Bn",
   "source": "youtube",
   "author": "@ahsanwani3353",
   "text": "is this real",
   "country": null
  },
  {
   "t_offset": 442.5,
   "external_id": "yt_ChwKGkNQbnJoZDNkdnBVREZhMTdUQWdkeXdvRXd3",
   "source": "youtube",
   "author": "@lonelysomeoneytofficial",
   "text": "hi cR7",
   "country": null
  },
  {
   "t_offset": 478.92,
   "external_id": "yt_ChwKGkNOeXd0dTdkdnBVREZjQmZUQWdkcjFvTE5n",
   "source": "youtube",
   "author": "@MohdJaved-iu2ox",
   "text": "kb chle gaa",
   "country": null
  },
  {
   "t_offset": 479.94,
   "external_id": "yt_ChwKGkNPZmY4ZTdkdnBVREZiN1Y1d01kT2NzQWdR",
   "source": "youtube",
   "author": "@4anas_____7",
   "text": "s",
   "country": null
  },
  {
   "t_offset": 483.6,
   "external_id": "yt_ChwKGkNLZXQwX0RkdnBVREZkZkF3Z1FkUE1RS293",
   "source": "youtube",
   "author": "@4anas_____7",
   "text": "v",
   "country": null
  },
  {
   "t_offset": 486.53,
   "external_id": "yt_ChwKGkNKSzdoUExkdnBVREZiQXNkZ1lkTHQ4TXhR",
   "source": "youtube",
   "author": "@4anas_____7",
   "text": "hlo",
   "country": null
  },
  {
   "t_offset": 502.6,
   "external_id": "yt_ChwKGkNJQ2EyUG5kdnBVREZlb1RyUVlkYlFJakR3",
   "source": "youtube",
   "author": "@Ivandelas434",
   "text": "is this real match",
   "country": null
  },
  {
   "t_offset": 504.55,
   "external_id": "yt_ChwKGkNJTDQwUHJkdnBVREZSdlB3Z1FkZlhjQWl3",
   "source": "youtube",
   "author": "@Birendrayt-x6b",
   "text": "hr",
   "country": null
  },
  {
   "t_offset": 508.51,
   "external_id": "yt_ChwKGkNPZTh4dnpkdnBVREZhSEtjZ2tkd2F3bEpR",
   "source": "youtube",
   "author": "@MR_REVELANTE",
   "text": "holaaa",
   "country": null
  },
  {
   "t_offset": 512.66,
   "external_id": "yt_ChwKGkNMWGx2XzdkdnBVREZjN0x3Z1FkRFFJZ0xB",
   "source": "youtube",
   "author": "@Ivandelas434",
   "text": "or not",
   "country": null
  },
  {
   "t_offset": 524.86,
   "external_id": "yt_ChwKGkNQbnFxNFRldnBVREZmeVV5d0VkekxNWDdB",
   "source": "youtube",
   "author": "@MR_REVELANTE",
   "text": "lamine yamal",
   "country": null
  },
  {
   "t_offset": 530.93,
   "external_id": "yt_ChwKGkNOZlpuSWZldnBVREZWM1F3Z1FkbDJNUnNR",
   "source": "youtube",
   "author": "@Ivandelas434",
   "text": "I also want to know",
   "country": null
  },
  {
   "t_offset": 540.62,
   "external_id": "yt_ChwKGkNQZm42SXZldnBVREZkZkF3Z1FkUE1RS293",
   "source": "youtube",
   "author": "@Ivandelas434",
   "text": "if real or not",
   "country": null
  },
  {
   "t_offset": 545.01,
   "external_id": "yt_ChwKGkNMVFE5WTNldnBVREZWX0l3Z1Fkbm5nUWF3",
   "source": "youtube",
   "author": "@Ivandelas434",
   "text": "tell",
   "country": null
  },
  {
   "t_offset": 549.76,
   "external_id": "yt_ChwKGkNPclNtNURldnBVREZjQ195d0VkQ2pJaGlR",
   "source": "youtube",
   "author": "@MR_REVELANTE",
   "text": "hello",
   "country": null
  },
  {
   "t_offset": 550.03,
   "external_id": "yt_ChwKGkNPV1ZxSkRldnBVREZSNDB6QVFkYlI4WTln",
   "source": "youtube",
   "author": "@Ivandelas434",
   "text": "some",
   "country": null
  },
  {
   "t_offset": 553.54,
   "external_id": "yt_ChwKGkNKdS1fWkhldnBVREZiN0h3Z1FkZVVvS1Fn",
   "source": "youtube",
   "author": "@Ivandelas434",
   "text": "one",
   "country": null
  },
  {
   "t_offset": 595.24,
   "external_id": "yt_ChwKGkNNU083YVhldnBVREZhWEw1d01kYUlJaVRn",
   "source": "youtube",
   "author": "@Ivandelas434",
   "text": "hhhhhh",
   "country": null
  },
  {
   "t_offset": 628.59,
   "external_id": "yt_ChwKGkNPM0JtYmpldnBVREZWNUJxd0lkbERnd3Z3",
   "source": "youtube",
   "author": "@SackKaarto",
   "text": "🇪🇸 🏆 ✌",
   "country": null
  },
  {
   "t_offset": 629.72,
   "external_id": "yt_ChwKGkNLcnAyTGpldnBVREZibC1UQWdkdF9vdVVn",
   "source": "youtube",
   "author": "@JONATHXNGAMINGYT",
   "text": "it's fake bro..",
   "country": null
  },
  {
   "t_offset": 642.38,
   "external_id": "yt_ChwKGkNOam0zYjdldnBVREZabGpUQWdkOEo4UkJ3",
   "source": "youtube",
   "author": "@JONATHXNGAMINGYT",
   "text": "match is about to start",
   "country": null
  },
  {
   "t_offset": 645.81,
   "external_id": "yt_ChwKGkNMei1zc0RldnBVREZYQldxd0lkdUs4VU93",
   "source": "youtube",
   "author": "@SackKaarto",
   "text": "ego Yamal fans",
   "country": null
  },
  {
   "t_offset": 657.97,
   "external_id": "yt_ChwKGkNOS3ltc2JldnBVREZRcmljZ2tkVnBVbEtn",
   "source": "youtube",
   "author": "@MR_REVELANTE",
   "text": "portugal",
   "country": null
  },
  {
   "t_offset": 664.49,
   "external_id": "yt_ChwKGkNMdmdvc25ldnBVREZhWEw1d01kYUlJaVRn",
   "source": "youtube",
   "author": "@1Just_meh.",
   "text": "is it fake??",
   "country": null
  },
  {
   "t_offset": 673.51,
   "external_id": "yt_ChwKGkNNYWJ5czNldnBVREZhenp3Z1FkRTZzVTRn",
   "source": "youtube",
   "author": "@JONATHXNGAMINGYT",
   "text": "yeah",
   "country": null
  },
  {
   "t_offset": 673.86,
   "external_id": "yt_ChwKGkNNZnI0TTNldnBVREZkN3p3Z1FkdV9JbERn",
   "source": "youtube",
   "author": "@LawraBhai-p6h",
   "text": "cr7boom boom",
   "country": null
  },
  {
   "t_offset": 678.35,
   "external_id": "yt_ChwKGkNQaUY4c19ldnBVREZkZkF3Z1FkUE1RS293",
   "source": "youtube",
   "author": "@animewhole982",
   "text": "z5",
   "country": null
  },
  {
   "t_offset": 679.88,
   "external_id": "yt_ChwKGkNNT0N6OURldnBVREZid1RyUVlkSmdrSHl3",
   "source": "youtube",
   "author": "@Btl10000",
   "text": "Spain",
   "country": null
  },
  {
   "t_offset": 682.79,
   "external_id": "yt_ChwKGkNJLVZnTkxldnBVREZZYno1d01kNEFNbENR",
   "source": "youtube",
   "author": "@thetablamaestro1676",
   "text": "🇦🇷🇦🇷🇦🇷",
   "country": null
  },
  {
   "t_offset": 689.79,
   "external_id": "yt_ChwKGkNQcmJydFhldnBVREZUbkN3Z1Fkd3VBTDRB",
   "source": "youtube",
   "author": "@Btl10000",
   "text": "Spain",
   "country": null
  },
  {
   "t_offset": 692.91,
   "external_id": "yt_ChwKGkNKTEQ2dGJldnBVREZVYkR3Z1FkQ1ZFNTVB",
   "source": "youtube",
   "author": "@Btl10000",
   "text": "Spain",
   "country": null
  },
  {
   "t_offset": 695.81,
   "external_id": "yt_ChwKGkNJbnFtdGpldnBVREZYM0h3Z1FkX0FNal93",
   "source": "youtube",
   "author": "@Btl10000",
   "text": "Spain",
   "country": null
  },
  {
   "t_offset": 698.62,
   "external_id": "yt_ChwKGkNLV055ZG5ldnBVREZadmV3Z1FkTDM0Q0Fn",
   "source": "youtube",
   "author": "@Btl10000",
   "text": "Spain",
   "country": null
  },
  {
   "t_offset": 702.88,
   "external_id": "yt_ChwKGkNMTEd5dHZldnBVREZSdkc1d01keEVnYVRn",
   "source": "youtube",
   "author": "@Btl10000",
   "text": "Spain",
   "country": null
  },
  {
   "t_offset": 703.63,
   "external_id": "yt_ChwKGkNKdmxfTnZldnBVREZWMGUxZ0FkOFBJVGp3",
   "source": "youtube",
   "author": "@АннаКравченко-ш3щ",
   "text": "фууу",
   "country": null
  },
  {
   "t_offset": 704.51,
   "external_id": "yt_ChwKGkNPSENyZHpldnBVREZXX0N3Z1FkMWZ3UzBB",
   "source": "youtube",
   "author": "@Btl10000",
   "text": "Spain",
   "country": null
  },
  {
   "t_offset": 707.53,
   "external_id": "yt_ChwKGkNNUHQ1ZDNldnBVREZXcmE1d01kdms0WU1R",
   "source": "youtube",
   "author": "@Btl10000",
   "text": "Spain",
   "country": null
  },
  {
   "t_offset": 711.05,
   "external_id": "yt_ChwKGkNPZkt2dF9ldnBVREZZZkV3Z1FkeVV3OHBB",
   "source": "youtube",
   "author": "@Btl10000",
   "text": "Spain",
   "country": null
  },
  {
   "t_offset": 711.83,
   "external_id": "yt_ChwKGkNMR3M3dF9ldnBVREZlZExUQWdkUHMwWFpR",
   "source": "youtube",
   "author": "@BhimDahal-x3b",
   "text": "is this channel upload real video",
   "country": null
  },
  {
   "t_offset": 713.61,
   "external_id": "yt_ChwKGkNNWDAyZURldnBVREZjSEd3Z1FkMGUwV2Fn",
   "source": "youtube",
   "author": "@Btl10000",
   "text": "Spain",
   "country": null
  },
  {
   "t_offset": 716.49,
   "external_id": "yt_ChwKGkNNejhpLUxldnBVREZlM2p3Z1FkdF9ZUGJR",
   "source": "youtube",
   "author": "@Btl10000",
   "text": "Spain",
   "country": null
  },
  {
   "t_offset": 719.8,
   "external_id": "yt_ChwKGkNPRDEwLVBldnBVREZXcmE1d01kdms0WU1R",
   "source": "youtube",
   "author": "@Btl10000",
   "text": "Spain",
   "country": null
  },
  {
   "t_offset": 722.21,
   "external_id": "yt_ChwKGkNQcVY1LVRldnBVREZWZ3FyUVlkaDhVbW93",
   "source": "youtube",
   "author": "@Btl10000",
   "text": "Spain",
   "country": null
  },
  {
   "t_offset": 724.81,
   "external_id": "yt_ChwKGkNKR2xnLWJldnBVREZmamk1d01kSUxFeldB",
   "source": "youtube",
   "author": "@Btl10000",
   "text": "Spain",
   "country": null
  },
  {
   "t_offset": 729.25,
   "external_id": "yt_ChwKGkNNaXBsdWpldnBVREZVX1p3Z1FkN09nVG9R",
   "source": "youtube",
   "author": "@Btl10000",
   "text": "Spain",
   "country": null
  },
  {
   "t_offset": 731.28,
   "external_id": "yt_ChwKGkNPVHBrT25ldnBVREZhYmg1d01kZW1vY3Nn",
   "source": "youtube",
   "author": "@Btl10000",
   "text": "Spain",
   "country": null
  },
  {
   "t_offset": 732.91,
   "external_id": "yt_ChwKGkNMeXc5ZW5ldnBVREZRWFB3Z1FkR2FNYkt3",
   "source": "youtube",
   "author": "@Btl10000",
   "text": "Spain",
   "country": null
  },
  {
   "t_offset": 736.36,
   "external_id": "yt_ChwKGkNOUFB5T3ZldnBVREZYalk1d01kdFZZeDhR",
   "source": "youtube",
   "author": "@Btl10000",
   "text": "Spain",
   "country": null
  },
  {
   "t_offset": 736.46,
   "external_id": "yt_ChwKGkNPMlQwdXZldnBVREZTNHQxZ0FkdFJVa1J3",
   "source": "youtube",
   "author": "@Sub2Noble",
   "text": "PORTUGAL WILL WIN",
   "country": null
  },
  {
   "t_offset": 737.32,
   "external_id": "yt_ChwKGkNJckVnZXpldnBVREZlTGV3Z1FkZ000ME1n",
   "source": "youtube",
   "author": "@JONATHXNGAMINGYT",
   "text": "no showing same video again n again",
   "country": null
  },
  {
   "t_offset": 738.4,
   "external_id": "yt_ChwKGkNJbXl3dXpldnBVREZjWU1kZ1lkYkJBYlZ3",
   "source": "youtube",
   "author": "@kinjit-c3r",
   "text": "portu",
   "country": null
  },
  {
   "t_offset": 738.45,
   "external_id": "yt_ChwKGkNOejh4ZXpldnBVREZmakc1d01kbnVzU0dB",
   "source": "youtube",
   "author": "@Btl10000",
   "text": "Spain",
   "country": null
  },
  {
   "t_offset": 741.44,
   "external_id": "yt_ChwKGkNLX1hfTzNldnBVREZmSEV3Z1FkU1FVeWFB",
   "source": "youtube",
   "author": "@LawraBhai-p6h",
   "text": "🇧🇷🇧🇷🇧🇷🇧🇷🇵🇹🇵🇹🇵🇹🇵🇹🇵🇹",
   "country": null
  },
  {
   "t_offset": 741.47,
   "external_id": "yt_ChwKGkNNVGdfZTNldnBVREZadlI1d01kd2pRWGx3",
   "source": "youtube",
   "author": "@AnuragSharma-t1b",
   "text": "portugal",
   "country": null
  },
  {
   "t_offset": 745.84,
   "external_id": "yt_ChwKGkNJZjFpdkRldnBVREZiY19yUVlkdkt3UTZB",
   "source": "youtube",
   "author": "@Btl10000",
   "text": "Spain",
   "country": null
  },
  {
   "t_offset": 747.8,
   "external_id": "yt_ChwKGkNJQ2FndkhldnBVREZhX0x3Z1FkZHdNNnln",
   "source": "youtube",
   "author": "@JONATHXNGAMINGYT",
   "text": "it's fake guys..",
   "country": null
  },
  {
   "t_offset": 748.2,
   "external_id": "yt_ChwKGkNNaWhuZkhldnBVREZhekhQd1FkTUpFdWxn",
   "source": "youtube",
   "author": "@АннаКравченко-ш3щ",
   "text": "🇦🇷🇦🇷🇦🇷ффуууу",
   "country": null
  },
  {
   "t_offset": 749.11,
   "external_id": "yt_ChwKGkNPeWQwUEhldnBVREZUckN3Z1FkeG1NYlJB",
   "source": "youtube",
   "author": "@Btl10000",
   "text": "Spain",
   "country": null
  },
  {
   "t_offset": 755.5,
   "external_id": "yt_ChwKGkNLR2YxdlRldnBVREZTX0N3Z1FkeF9Fbkxn",
   "source": "youtube",
   "author": "@Btl10000",
   "text": "Spain are playing up",
   "country": null
  },
  {
   "t_offset": 758.75,
   "external_id": "yt_ChwKGkNQblNuZmJldnBVREZTam81d01kcGZjMzFB",
   "source": "youtube",
   "author": "@Btl10000",
   "text": "Spain",
   "country": null
  },
  {
   "t_offset": 762.21,
   "external_id": "yt_ChwKGkNLak04X2ZldnBVREZUakJ3Z1FkX1FneHBn",
   "source": "youtube",
   "author": "@Btl10000",
   "text": "Spain",
   "country": null
  },
  {
   "t_offset": 764.77,
   "external_id": "yt_ChwKGkNJQ3NqX25ldnBVREZiWHk1d01kMEFBR3Bn",
   "source": "youtube",
   "author": "@Btl10000",
   "text": "Spain",
   "country": null
  },
  {
   "t_offset": 770.32,
   "external_id": "yt_ChwKGkNJWDEzZnZldnBVREZhenp3Z1FkRTZzVTRn",
   "source": "youtube",
   "author": "@LawraBhai-p6h",
   "text": "🇵🇹🇵🇹🇵🇹🇵🇹",
   "country": null
  },
  {
   "t_offset": 772.15,
   "external_id": "yt_ChwKGkNMQ2QwX3pldnBVREZlZkRQd1FkanQ0V253",
   "source": "youtube",
   "author": "@Sub2Noble",
   "text": "Ronaldo hat trick",
   "country": null
  },
  {
   "t_offset": 773.65,
   "external_id": "yt_ChwKGkNMbW5xdjNldnBVREZTMXlUQWdkbUtBMVBn",
   "source": "youtube",
   "author": "@sathishkumarkasiviswanatha9266",
   "text": "set-up",
   "country": null
  },
  {
   "t_offset": 774.71,
   "external_id": "yt_ChwKGkNOT0c2djNldnBVREZUb296QVFkYktRMXZR",
   "source": "youtube",
   "author": "@BhimDahal-x3b",
   "text": "is this channel upload real match video",
   "country": null
  },
  {
   "t_offset": 777.41,
   "external_id": "yt_ChwKGkNOVDBrdl9ldnBVREZXVVlyUVlkZE1nN1FR",
   "source": "youtube",
   "author": "@Btl10000",
   "text": "vote for Spain",
   "country": null
  },
  {
   "t_offset": 778.41,
   "external_id": "yt_ChwKGkNKckx6Zl9ldnBVREZSX0N3Z1FkSnUwMzNn",
   "source": "youtube",
   "author": "@Btl10000",
   "text": "Spain",
   "country": null
  },
  {
   "t_offset": 781.42,
   "external_id": "yt_ChwKGkNKcUhoNEhmdnBVREZSekl3Z1FkQ1R3OWF3",
   "source": "youtube",
   "author": "@Btl10000",
   "text": "Spain",
   "country": null
  },
  {
   "t_offset": 784.91,
   "external_id": "yt_ChwKGkNMMnIzSUxmdnBVREZWM0h3Z1FkLWNBZ2tR",
   "source": "youtube",
   "author": "@Btl10000",
   "text": "Spain",
   "country": null
  },
  {
   "t_offset": 785.58,
   "external_id": "yt_ChwKGkNPdmJoNFBmdnBVREZjdmRjZ2tkeHRnYTVn",
   "source": "youtube",
   "author": "@MR_REVELANTE",
   "text": "round",
   "country": null
  },
  {
   "t_offset": 786.86,
   "external_id": "yt_ChwKGkNKYUIwSVBmdnBVREZWM0h3Z1FkLWNBZ2tR",
   "source": "youtube",
   "author": "@Btl10000",
   "text": "sp",
   "country": null
  },
  {
   "t_offset": 791.4,
   "external_id": "yt_ChwKGkNNYTE1b1hmdnBVREZaclB3Z1FkMWVZMUpR",
   "source": "youtube",
   "author": "@Btl10000",
   "text": "Spain",
   "country": null
  },
  {
   "t_offset": 792.25,
   "external_id": "yt_ChwKGkNJRDFtb2JmdnBVREZUVVhkZ1lkZm5jeGVn",
   "source": "youtube",
   "author": "@Btl10000",
   "text": "Spain",
   "country": null
  },
  {
   "t_offset": 794.63,
   "external_id": "yt_ChwKGkNQVHFyWWZmdnBVREZUelF3Z1FkZ0E0bjNn",
   "source": "youtube",
   "author": "@Btl10000",
   "text": "Spain",
   "country": null
  },
  {
   "t_offset": 797.87,
   "external_id": "yt_ChwKGkNKcU44b2pmdnBVREZVVGV3Z1Fkb3JJeGx3",
   "source": "youtube",
   "author": "@Btl10000",
   "text": "Spain",
   "country": null
  },
  {
   "t_offset": 799.44,
   "external_id": "yt_ChwKGkNQZmgwWW5mdnBVREZhenp3Z1FkRTZzVTRn",
   "source": "youtube",
   "author": "@Nunthemlhouvum-o7y",
   "text": "SPAINESE",
   "country": null
  },
  {
   "t_offset": 801.74,
   "external_id": "yt_ChwKGkNPalozb3JmdnBVREZTX0N3Z1FkeF9Fbkxn",
   "source": "youtube",
   "author": "@Btl10000",
   "text": "Spain",
   "country": null
  },
  {
   "t_offset": 804.79,
   "external_id": "yt_ChwKGkNLR2ZsNHpmdnBVREZkZkF3Z1FkUE1RS293",
   "source": "youtube",
   "author": "@LawraBhai-p6h",
   "text": "CR7goat",
   "country": null
  },
  {
   "t_offset": 804.97,
   "external_id": "yt_ChwKGkNKbTlwSXpmdnBVREZXcmE1d01kdms0WU1R",
   "source": "youtube",
   "author": "@Btl10000",
   "text": "Spain",
   "country": null
  },
  {
   "t_offset": 808.92,
   "external_id": "yt_ChwKGkNKMnlsSTdmdnBVREZZYno1d01kNEFNbENR",
   "source": "youtube",
   "author": "@ReshmaChaudhary-f2m",
   "text": "this video is real or fake",
   "country": null
  },
  {
   "t_offset": 812.03,
   "external_id": "yt_ChwKGkNMYTcwSV9mdnBVREZSN0E1d01kb0hNUkZ3",
   "source": "youtube",
   "author": "@Btl10000",
   "text": "Spain",
   "country": null
  },
  {
   "t_offset": 817.7,
   "external_id": "yt_ChwKGkNMLURySkxmdnBVREZiY19yUVlkdkt3UTZB",
   "source": "youtube",
   "author": "@LawraBhai-p6h",
   "text": "cr7",
   "country": null
  },
  {
   "t_offset": 818.18,
   "external_id": "yt_ChwKGkNMUHR5SkxmdnBVREZTWEV3Z1FkVnhnN1Fn",
   "source": "youtube",
   "author": "@KenzaSurayya",
   "text": "messiiiiiiiiiiiiiiiiiiiiiiiiiiiiiiiiiiiiiiiiiiiiiiiiiiiiiiiiiiiiiiiiiiiiiiiiiiiiiiiiiiiiiiiiiiiiiiiiiiiiiiiiiiiiiiiiiiiiiiiiiiiiiiiiiiiiiiiiiiiiiiiiiiiiiiiiiiiiiiiiiiiiiiiiiiiiiiiiiiiiiiiiiiiiiiiiiiii",
   "country": null
  },
  {
   "t_offset": 820.48,
   "external_id": "yt_ChwKGkNKcVYxWlBmdnBVREZZZkV3Z1FkeVV3OHBB",
   "source": "youtube",
   "author": "@Btl10000",
   "text": "Spain Spain Spain Spain Spain Spain",
   "country": null
  },
  {
   "t_offset": 823.19,
   "external_id": "yt_ChwKGkNOU3gtNVRmdnBVREZWM0h3Z1FkLWNBZ2tR",
   "source": "youtube",
   "author": "@LawraBhai-p6h",
   "text": "cr7",
   "country": null
  },
  {
   "t_offset": 825.3,
   "external_id": "yt_ChwKGkNMblhfWlhmdnBVREZYM0h3Z1FkX0FNal93",
   "source": "youtube",
   "author": "@Btl10000",
   "text": "Spain Spain",
   "country": null
  },
  {
   "t_offset": 832.66,
   "external_id": "yt_ChwKGkNKdTJ2cG5mdnBVREZUckN3Z1FkeG1NYlJB",
   "source": "youtube",
   "author": "@Btl10000",
   "text": "Spainnnnnnnnnnnnnnn",
   "country": null
  },
  {
   "t_offset": 833.78,
   "external_id": "yt_ChwKGkNLYkxnSnJmdnBVREZRdkR3Z1FkU1Nja2hn",
   "source": "youtube",
   "author": "@KenzaSurayya",
   "text": "nooooooooooooo",
   "country": null
  },
  {
   "t_offset": 834.88,
   "external_id": "yt_ChwKGkNKckp4cHJmdnBVREZWb19yUVlkNHZvdERB",
   "source": "youtube",
   "author": "@manoharprasadchaudhary7248",
   "text": "offcoure real",
   "country": null
  },
  {
   "t_offset": 843.62,
   "external_id": "yt_ChwKGkNNTzgySjdmdnBVREZlTFB3Z1FkUHNROTRR",
   "source": "youtube",
   "author": "@lonelysomeoneytofficial",
   "text": "fack video 😡😡😡😡",
   "country": null
  },
  {
   "t_offset": 851.3,
   "external_id": "yt_ChwKGkNNS1ZycUxmdnBVREZTSWhkZ1lkUVl3cVhR",
   "source": "youtube",
   "author": "@Btl10000",
   "text": "Spainnnnnnnnnnnnnnnnnnnnnnnnnnnnnnnnnnnnnennnnnnnnnnnnnnnnn nnnnnn",
   "country": null
  },
  {
   "t_offset": 855.68,
   "external_id": "yt_ChwKGkNQQ2x2S1RmdnBVREZadmZ3Z1FkamU4MmF3",
   "source": "youtube",
   "author": "@KenzaSurayya",
   "text": "your spain",
   "country": null
  },
  {
   "t_offset": 858.92,
   "external_id": "yt_ChwKGkNPS01ncWJmdnBVREZZY3hkZ1lkaFBZOEZ3",
   "source": "youtube",
   "author": "@AlsonRai-u8j8k",
   "text": "🇵🇹",
   "country": null
  },
  {
   "t_offset": 871.15,
   "external_id": "yt_ChwKGkNKblU2YXZmdnBVREZjZkh3Z1FkUlFncHln",
   "source": "youtube",
   "author": "@ALOKBARLA-j3d",
   "text": "CR 7 god",
   "country": null
  },
  {
   "t_offset": 872.83,
   "external_id": "yt_ChwKGkNQZW8wYXpmdnBVREZRM1hMUUFkNTJBdnln",
   "source": "youtube",
   "author": "@AlsonRai-u8j8k",
   "text": "🇵🇹",
   "country": null
  },
  {
   "t_offset": 875.49,
   "external_id": "yt_ChwKGkNONl85NjNmdnBVREZab2kxZ0FkdEhRUmpB",
   "source": "youtube",
   "author": "@LaurentSaints",
   "text": "is this real?",
   "country": null
  },
  {
   "t_offset": 876.59,
   "external_id": "yt_ChwKGkNPTEp0YTdmdnBVREZUelR3Z1FkT2I0c293",
   "source": "youtube",
   "author": "@Btl10000",
   "text": "star",
   "country": null
  },
  {
   "t_offset": 879.61,
   "external_id": "yt_ChwKGkNJYmk4S19mdnBVREZUelF3Z1FkZ0E0bjNn",
   "source": "youtube",
   "author": "@LawraBhai-p6h",
   "text": "hey kids goat always goat you know that's goat is cr7",
   "country": null
  },
  {
   "t_offset": 880.14,
   "external_id": "yt_ChwKGkNQXzhqckRmdnBVREZaclB3Z1FkMWVZMUpR",
   "source": "youtube",
   "author": "@ReshmaChaudhary-f2m",
   "text": "CR7",
   "country": null
  },
  {
   "t_offset": 886.67,
   "external_id": "yt_ChwKGkNKbU1uclBmdnBVREZYNzA1d01kMFdnZDJn",
   "source": "youtube",
   "author": "@Btl10000",
   "text": "young star",
   "country": null
  },
  {
   "t_offset": 886.96,
   "external_id": "yt_ChwKGkNLLV9zYlBmdnBVREZUelR3Z1FkT2I0c293",
   "source": "youtube",
   "author": "@lonelysomeoneytofficial",
   "text": "I'm now in Z5 , this is fack video 😡😡😡",
   "country": null
  },
  {
   "t_offset": 891.95,
   "external_id": "yt_ChwKGkNPcmozN1hmdnBVREZSekl3Z1FkQ1R3OWF3",
   "source": "youtube",
   "author": "@KenzaSurayya",
   "text": "mmmmm",
   "country": null
  },
  {
   "t_offset": 893.25,
   "external_id": "yt_ChwKGkNKTzlycmJmdnBVREZkakx3Z1FkNTJZaWNR",
   "source": "youtube",
   "author": "@Sarathisarkar-h8o",
   "text": "mach must start now",
   "country": null
  },
  {
   "t_offset": 894.91,
   "external_id": "yt_ChwKGkNMdnZrN2ZmdnBVREZielY1d01kaGJZM2ZR",
   "source": "youtube",
   "author": "@Btl10000",
   "text": "young star",
   "country": null
  },
  {
   "t_offset": 899.7,
   "external_id": "yt_ChwKGkNKV2t1N25mdnBVREZWX0l3Z1Fkbm5nUWF3",
   "source": "youtube",
   "author": "@Sarathisarkar-h8o",
   "text": "its fake",
   "country": null
  },
  {
   "t_offset": 900.18,
   "external_id": "yt_ChwKGkNNbmoxN25mdnBVREZiWHk1d01kMEFBR3Bn",
   "source": "youtube",
   "author": "@Btl10000",
   "text": ":face-red-droopy-eyes:",
   "country": null
  },
  {
   "t_offset": 902.58,
   "external_id": "yt_ChwKGkNPNi02THJmdnBVREZWb19yUVlkNHZvdERB",
   "source": "youtube",
   "author": "@Btl10000",
   "text": ":face-orange-raised-eyebrow:",
   "country": null
  },
  {
   "t_offset": 905.17,
   "external_id": "yt_ChwKGkNQSHpoN3pmdnBVREZRdkR3Z1FkU1Nja2hn",
   "source": "youtube",
   "author": "@Btl10000",
   "text": ":face-orange-raised-eyebrow:",
   "country": null
  },
  {
   "t_offset": 907.67,
   "external_id": "yt_ChwKGkNQdWVuNzNmdnBVREZaWEh3Z1FkaURjVFFn",
   "source": "youtube",
   "author": "@PreetiSingh-ws1yw",
   "text": "is this real?",
   "country": null
  },
  {
   "t_offset": 910.97,
   "external_id": "yt_ChwKGkNKbTA2TDdmdnBVREZUTFM1d01kUHlzckh3",
   "source": "youtube",
   "author": "@Btl10000",
   "text": ":face-fuchsia-tongue-out:",
   "country": null
  },
  {
   "t_offset": 913.59,
   "external_id": "yt_ChwKGkNMZk5pTURmdnBVREZkakx3Z1FkNTJZaWNR",
   "source": "youtube",
   "author": "@Btl10000",
   "text": ":text-green-game-over:",
   "country": null
  },
  {
   "t_offset": 914.09,
   "external_id": "yt_ChwKGkNJZmJwc0RmdnBVREZlTFN3Z1Fka0VVUjNR",
   "source": "youtube",
   "author": "@PreetiSingh-ws1yw",
   "text": "i dont think so",
   "country": null
  },
  {
   "t_offset": 915.89,
   "external_id": "yt_ChwKGkNJdVdsY0hmdnBVREZRM1A1d01kYllNYTlB",
   "source": "youtube",
   "author": "@Btl10000",
   "text": ":text-green-game-over:",
   "country": null
  },
  {
   "t_offset": 918.47,
   "external_id": "yt_ChwKGkNJRFJzY0xmdnBVREZkY2NkZ1lkQU5nUmdR",
   "source": "youtube",
   "author": "@Btl10000",
   "text": ":face-green-smiling:",
   "country": null
  },
  {
   "t_offset": 920.36,
   "external_id": "yt_ChwKGkNQYUVwY1BmdnBVREZkN3p3Z1FkdV9JbERn",
   "source": "youtube",
   "author": "@Btl10000",
   "text": ":person-turqouise-waving:",
   "country": null
  },
  {
   "t_offset": 923.27,
   "external_id": "yt_ChwKGkNKR0oxOFRmdnBVREZTSWhkZ1lkUVl3cVhR",
   "source": "youtube",
   "author": "@Btl10000",
   "text": ":face-green-smiling:",
   "country": null
  },
  {
   "t_offset": 928.21,
   "external_id": "yt_ChwKGkNPbXBoTWZmdnBVREZaakV3Z1FkN3BjbEN3",
   "source": "youtube",
   "author": "@Btl10000",
   "text": ":face-fuchsia-tongue-out::face-blue-wide-eyes::cat-orange-whistling::face-blue-wide-eyes::text-green-game-over:",
   "country": null
  },
  {
   "t_offset": 934.09,
   "external_id": "yt_ChwKGkNLdnE2c25mdnBVREZkQV9yUVlkM2RZdktR",
   "source": "youtube",
   "author": "@Btl10000",
   "text": ":face-green-smiling::face-green-smiling:",
   "country": null
  },
  {
   "t_offset": 936.86,
   "external_id": "yt_ChwKGkNOYjdsc3ZmdnBVREZjMHl6QVFkQ2RvM0tR",
   "source": "youtube",
   "author": "@Btl10000",
   "text": ":face-orange-raised-eyebrow::face-orange-raised-eyebrow::face-orange-raised-eyebrow:",
   "country": null
  },
  {
   "t_offset": 939.99,
   "external_id": "yt_ChwKGkNKLTkwc3pmdnBVREZjZlk1d01kbG1zWFZn",
   "source": "youtube",
   "author": "@Btl10000",
   "text": ":face-green-smiling::face-green-smiling::face-green-smiling:",
   "country": null
  },
  {
   "t_offset": 943.05,
   "external_id": "yt_ChwKGkNLM19qODdmdnBVREZYN0l3Z1FkU21NZ0pR",
   "source": "youtube",
   "author": "@Btl10000",
   "text": ":face-fuchsia-tongue-out::face-fuchsia-tongue-out::face-fuchsia-tongue-out:",
   "country": null
  },
  {
   "t_offset": 950.92,
   "external_id": "yt_ChwKGkNQV0Q4ZEhmdnBVREZYTEV3Z1FkM3pNclJB",
   "source": "youtube",
   "author": "@Btl10000",
   "text": ":face-blue-wide-eyes::face-blue-wide-eyes::face-blue-wide-eyes:",
   "country": null
  },
  {
   "t_offset": 953.17,
   "external_id": "yt_ChwKGkNKLUEtTkxmdnBVREZiVEQ1d01kRTFvYVl3",
   "source": "youtube",
   "author": "@lonelysomeoneytofficial",
   "text": "live link",
   "country": null
  },
  {
   "t_offset": 994.62,
   "external_id": "yt_ChwKGkNLQ0MydWJmdnBVREZkN3p3Z1FkdV9JbERn",
   "source": "youtube",
   "author": "@lonelysomeoneytofficial",
   "text": "free in ip tv",
   "country": null
  },
  {
   "t_offset": 997.93,
   "external_id": "yt_ChwKGkNJUGxwdWpmdnBVREZlb1RyUVlkYlFJakR3",
   "source": "youtube",
   "author": "@ThinChuk-f8e",
   "text": "bonjure",
   "country": null
  },
  {
   "t_offset": 1001.32,
   "external_id": "yt_ChwKGkNPZnA5ZW5mdnBVREZTWEV3Z1FkVnhnN1Fn",
   "source": "youtube",
   "author": "@SasiK-z7o",
   "text": "start the game",
   "country": null
  },
  {
   "t_offset": 1013.53,
   "external_id": "yt_ChwKGkNLT2QyLV9mdnBVREZUQV9yUVlkb2l3SFFB",
   "source": "youtube",
   "author": "@lonelysomeoneytofficial",
   "text": "fack steaming 😡😡😡😡😡",
   "country": null
  },
  {
   "t_offset": 1015.73,
   "external_id": "yt_ChwKGkNOU0o0X0RmdnBVREZZdnl3Z1FkcDJFVUF3",
   "source": "youtube",
   "author": "@Btl10000",
   "text": "start",
   "country": null
  },
  {
   "t_offset": 1026.29,
   "external_id": "yt_ChwKGkNOT2M1dlhmdnBVREZUelF3Z1FkZ0E0bjNn",
   "source": "youtube",
   "author": "@Birendrayt-x6b",
   "text": "hlo guys",
   "country": null
  },
  {
   "t_offset": 1026.87,
   "external_id": "yt_ChwKGkNMR1FqUGJmdnBVREZmZkI1d01kN08wd1Bn",
   "source": "youtube",
   "author": "@Btl10000",
   "text": "sulululululululul",
   "country": null
  },
  {
   "t_offset": 1028.02,
   "external_id": "yt_ChwKGkNJUDl6X2JmdnBVREZUWG01d01kc0xZS2VB",
   "source": "youtube",
   "author": "@SasiK-z7o",
   "text": "yes",
   "country": null
  },
  {
   "t_offset": 1031.66,
   "external_id": "yt_ChwKGkNPN0pydmpmdnBVREZWNzM1d01kY2xJeG5n",
   "source": "youtube",
   "author": "@Btl10000",
   "text": "helo",
   "country": null
  },
  {
   "t_offset": 1041.33,
   "external_id": "yt_ChwKGkNJZUFfZnpmdnBVREZVVGV3Z1Fkb3JJeGx3",
   "source": "youtube",
   "author": "@Birendrayt-x6b",
   "text": "💚💚",
   "country": null
  },
  {
   "t_offset": 1045.17,
   "external_id": "yt_ChwKGkNLVEk1XzdmdnBVREZjamw1d01kc0E4bVZB",
   "source": "youtube",
   "author": "@Btl10000",
   "text": "who are you",
   "country": null
  },
  {
   "t_offset": 1046.08,
   "external_id": "yt_ChwKGkNPM0duX19mdnBVREZRdkR3Z1FkU1Nja2hn",
   "source": "youtube",
   "author": "@SasiK-z7o",
   "text": "not start",
   "country": null
  },
  {
   "t_offset": 1054.73,
   "external_id": "yt_ChwKGkNQejNyb1BndnBVREZaWEh3Z1FkaURjVFFn",
   "source": "youtube",
   "author": "@Birendrayt-x6b",
   "text": "sanchoi xaou kataa ho",
   "country": null
  },
  {
   "t_offset": 1055.74,
   "external_id": "yt_ChwKGkNKSFk3NFBndnBVREZSYkNMUUFkLUZ3eTl3",
   "source": "youtube",
   "author": "@KenzaSurayya",
   "text": "start:face-red-droopy-eyes:",
   "country": null
  },
  {
   "t_offset": 1058.81,
   "external_id": "yt_ChwKGkNMbm9xSVhndnBVREZaREl3Z1FkT29FZFRR",
   "source": "youtube",
   "author": "@SasiK-z7o",
   "text": "I am",
   "country": null
  },
  {
   "t_offset": 1069.84,
   "external_id": "yt_ChwKGkNKdXl5WXJndnBVREZXd3NkZ1lkOUljOGt3",
   "source": "youtube",
   "author": "@VarshithVV-f7r",
   "text": "hello",
   "country": null
  },
  {
   "t_offset": 1070.45,
   "external_id": "yt_ChwKGkNMeUg4SXJndnBVREZjSEd3Z1FkMGUwV2Fn",
   "source": "youtube",
   "author": "@Birendrayt-x6b",
   "text": "Maya xaa laa",
   "country": null
  },
  {
   "t_offset": 1078.64,
   "external_id": "yt_ChwKGkNQdkE0bzdndnBVREZVaE9UQWdkQkFReEl3",
   "source": "youtube",
   "author": "@KenzaSurayya",
   "text": "me",
   "country": null
  },
  {
   "t_offset": 1084.23,
   "external_id": "yt_ChwKGkNMMmV1cEhndnBVREZTREJ3Z1Fkc3pNQ0FR",
   "source": "youtube",
   "author": "@Btl10000",
   "text": "sp",
   "country": null
  },
  {
   "t_offset": 1087.1,
   "external_id": "yt_ChwKGkNNXzE1NUxndnBVREZTa29kZ1lkSkU4N2tn",
   "source": "youtube",
   "author": "@Birendrayt-x6b",
   "text": "All guys Lai Maya xaa laq",
   "country": null
  },
  {
   "t_offset": 1087.53,
   "external_id": "yt_ChwKGkNOYjBnWlBndnBVREZmUFB3Z1FkekJzUHh3",
   "source": "youtube",
   "author": "@Tenzinkyinzom-sf4it",
   "text": "suiii",
   "country": null
  },
  {
   "t_offset": 1099.95,
   "external_id": "yt_ChwKGkNMRHA5NWpndnBVREZTREJ3Z1Fkc3pNQ0FR",
   "source": "youtube",
   "author": "@Birendrayt-x6b",
   "text": "sulll",
   "country": null
  },
  {
   "t_offset": 1107.27,
   "external_id": "yt_ChwKGkNPREd0SnpndnBVREZWZ3FyUVlkaDhVbW93",
   "source": "youtube",
   "author": "@Birendrayt-x6b",
   "text": "suluuuuuuu",
   "country": null
  },
  {
   "t_offset": 1128.49,
   "external_id": "yt_ChwKGkNKemJ4cWJndnBVREZVdkV3Z1FkRk5vSWh3",
   "source": "youtube",
   "author": "@Birendrayt-x6b",
   "text": "💚",
   "country": null
  },
  {
   "t_offset": 1132.33,
   "external_id": "yt_ChwKGkNLcVFzcWpndnBVREZWM0h3Z1FkLWNBZ2tR",
   "source": "youtube",
   "author": "@Birendrayt-x6b",
   "text": ":hand-pink-waving:",
   "country": null
  },
  {
   "t_offset": 1136.56,
   "external_id": "yt_ChwKGkNLajJzcXJndnBVREZYN0l3Z1FkU21NZ0pR",
   "source": "youtube",
   "author": "@Birendrayt-x6b",
   "text": ":hand-pink-waving::hand-pink-waving:",
   "country": null
  },
  {
   "t_offset": 1169.33,
   "external_id": "yt_ChwKGkNKUExncnJndnBVREZiWHk1d01kMEFBR3Bn",
   "source": "youtube",
   "author": "@manoj18Nayk",
   "text": "match start nai huwaa abii tak",
   "country": null
  },
  {
   "t_offset": 1201.83,
   "external_id": "yt_ChwKGkNQQzl3OG5ndnBVREZjSEd3Z1FkMGUwV2Fn",
   "source": "youtube",
   "author": "@mahekdqueen2638",
   "text": "suuuuiiiiiiiii❤",
   "country": null
  },
  {
   "t_offset": 1213.91,
   "external_id": "yt_ChwKGkNJM3JwY19ndnBVREZZY3hkZ1lkaFBZOEZ3",
   "source": "youtube",
   "author": "@mahekdqueen2638",
   "text": "Cr7",
   "country": null
  },
  {
   "t_offset": 1224.79,
   "external_id": "yt_ChwKGkNQNm52ZFRndnBVREZlRFo1d01kWlA0cnZn",
   "source": "youtube",
   "author": "@mahekdqueen2638",
   "text": "suiiiiiii",
   "country": null
  },
  {
   "t_offset": 1226.07,
   "external_id": "yt_ChwKGkNMSzJpTlhndnBVREZjejB3Z1FkWTZNTGdR",
   "source": "youtube",
   "author": "@SidraSuthana-p6x",
   "text": "didn't match start already",
   "country": null
  },
  {
   "t_offset": 1234.79,
   "external_id": "yt_ChwKGkNQNkNuZG5ndnBVREZVdkV3Z1FkRk5vSWh3",
   "source": "youtube",
   "author": "@SuparnaGhosh-b4q",
   "text": "cr7",
   "country": null
  },
  {
   "t_offset": 1245.9,
   "external_id": "yt_ChwKGkNOT3F4dDdndnBVREZlb1RyUVlkYlFJakR3",
   "source": "youtube",
   "author": "@DavidDui-p5u9d",
   "text": "spain 🇪🇸",
   "country": null
  },
  {
   "t_offset": 1250.67,
   "external_id": "yt_ChwKGkNKM0E2T0RndnBVREZUbkN3Z1FkS3hJS0N3",
   "source": "youtube",
   "author": "@SidraSuthana-p6x",
   "text": "match started",
   "country": null
  },
  {
   "t_offset": 1251.38,
   "external_id": "yt_ChwKGkNQS1hrLUhndnBVREZRdkR3Z1FkU1Nja2hn",
   "source": "youtube",
   "author": "@GingneTallang",
   "text": "ronaldo suuuiii",
   "country": null
  },
  {
   "t_offset": 1276.99,
   "external_id": "yt_ChwKGkNNLUxydTNndnBVREZiVEQ1d01kRTFvYVl3",
   "source": "youtube",
   "author": "@LokeshDarwatkar-q4b",
   "text": "match start kab hogi",
   "country": null
  },
  {
   "t_offset": 1280.34,
   "external_id": "yt_ChwKGkNQdWQtLTdndnBVREZUX0N3Z1FkajBzcGlR",
   "source": "youtube",
   "author": "@GingneTallang",
   "text": "spain booooo👎🏼👎🏼👎🏼👎🏼",
   "country": null
  },
  {
   "t_offset": 1303.02,
   "external_id": "yt_ChwKGkNPaWQ0X25ndnBVREZWX0l3Z1Fkbm5nUWF3",
   "source": "youtube",
   "author": "@JamshenaMdr",
   "text": "link",
   "country": null
  },
  {
   "t_offset": 1304.11,
   "external_id": "yt_ChwKGkNMR2ZwdnJndnBVREZSYnQ1d01kTkNzN3VR",
   "source": "youtube",
   "author": "@makeamasti6166",
   "text": "binod",
   "country": null
  },
  {
   "t_offset": 1317.55,
   "external_id": "yt_ChwKGkNMelAyWURodnBVREZVWER3Z1FkNEdnNG93",
   "source": "youtube",
   "author": "@SumitharS-x3i",
   "text": ":face-blue-smiling:",
   "country": null
  },
  {
   "t_offset": 1328.53,
   "external_id": "yt_ChwKGkNPelctWVhodnBVREZaREl3Z1FkT29FZFRR",
   "source": "youtube",
   "author": "@JamshenaMdr",
   "text": "link",
   "country": null
  },
  {
   "t_offset": 1360.97,
   "external_id": "yt_ChwKGkNMYl90SlhodnBVREZVVGV3Z1Fkb3JJeGx3",
   "source": "youtube",
   "author": "@HirakDeka-t5w",
   "text": "link",
   "country": null
  },
  {
   "t_offset": 1381.5,
   "external_id": "yt_ChwKGkNNTzBtWl9odnBVREZUelF3Z1FkZ0E0bjNn",
   "source": "youtube",
   "author": "@ReshmaChaudhary-f2m",
   "text": "match kab start hogii",
   "country": null
  },
  {
   "t_offset": 1386.43,
   "external_id": "yt_ChwKGkNOYlh5cUhodnBVREZVeldQd1FkVVI0Z2xn",
   "source": "youtube",
   "author": "@fdickie",
   "text": "This is face the game already started",
   "country": null
  },
  {
   "t_offset": 1393.85,
   "external_id": "yt_ChwKGkNKMjBpNlhodnBVREZmZ1lyUVlkVVFBazVn",
   "source": "youtube",
   "author": "@HBTYHT",
   "text": "FIFA WORLD CUP LIVE👉 𝐄𝐒𝐏𝐍𝐓𝐕𝐒,𝐂𝐎̷𝐌 :face-turquoise-drinking-coffee::face-turquoise-drinking-coffee::face-turquoise-drinking-coffee:",
   "country": null
  },
  {
   "t_offset": 1394.1,
   "external_id": "yt_ChwKGkNNMlZtcVhodnBVREZjWU1kZ1lkYkJBYlZ3",
   "source": "youtube",
   "author": "@HBTYHT",
   "text": "FIFA WORLD CUP LIVE👉 𝐄𝐒𝐏𝐍𝐓𝐕𝐒,𝐂𝐎̷𝐌 :face-turquoise-drinking-coffee::face-turquoise-drinking-coffee::face-turquoise-drinking-coffee:",
   "country": null
  },
  {
   "t_offset": 1394.28,
   "external_id": "yt_ChwKGkNKUFZwYVhodnBVREZlTFB3Z1FkUHNROTRR",
   "source": "youtube",
   "author": "@HBTYHT",
   "text": "FIFA WORLD CUP LIVE👉 𝐄𝐒𝐏𝐍𝐓𝐕𝐒,𝐂𝐎̷𝐌 :face-turquoise-drinking-coffee::face-turquoise-drinking-coffee::face-turquoise-drinking-coffee:",
   "country": null
  },
  {
   "t_offset": 1394.72,
   "external_id": "yt_ChwKGkNMYTZ3cVhodnBVREZUelF3Z1FkZ0E0bjNn",
   "source": "youtube",
   "author": "@HBTYHT",
   "text": "FIFA WORLD CUP LIVE👉 𝐄𝐒𝐏𝐍𝐓𝐕𝐒,𝐂𝐎̷𝐌 :face-turquoise-drinking-coffee::face-turquoise-drinking-coffee::face-turquoise-drinking-coffee:",
   "country": null
  },
  {
   "t_offset": 1396.01,
   "external_id": "yt_ChwKGkNKV3FrS2JodnBVREZUX0N3Z1FkajBzcGlR",
   "source": "youtube",
   "author": "@HBTYHT",
   "text": "FIFA WORLD CUP LIVE👉 𝐄𝐒𝐏𝐍𝐓𝐕𝐒,𝐂𝐎̷𝐌 :face-turquoise-drinking-coffee::face-turquoise-drinking-coffee::face-turquoise-drinking-coffee:",
   "country": null
  },
  {
   "t_offset": 1399.23,
   "external_id": "yt_ChwKGkNLai0xYWZodnBVREZUelF3Z1FkZ0E0bjNn",
   "source": "youtube",
   "author": "@ReshmaChaudhary-f2m",
   "text": "same video Chala rahe haii repeat kar kar k",
   "country": null
  },
  {
   "t_offset": 1402.28,
   "external_id": "yt_ChwKGkNORGNqYW5odnBVREZVX0U1d01kZnVBTm1n",
   "source": "youtube",
   "author": "@SulekhaMaity-g6f",
   "text": "huiiu",
   "country": null
  },
  {
   "t_offset": 1420.0,
   "external_id": "yt_ChwKGkNKWEV5ckhodnBVREZUelR3Z1FkT2I0c293",
   "source": "youtube",
   "author": "@MOKHTARAHMAD-t6s",
   "text": "bhai ye official hai",
   "country": null
  },
  {
   "t_offset": 1449.39,
   "external_id": "yt_ChwKGkNOR2t5N19odnBVREZUX0N3Z1FkajBzcGlR",
   "source": "youtube",
   "author": "@dhavalbhinde4336",
   "text": "real ????",
   "country": null
  },
  {
   "t_offset": 1505.1,
   "external_id": "yt_ChwKGkNKbk9rdHJodnBVREZURFF3Z1FkTTNJeGl3",
   "source": "youtube",
   "author": "@opbhavyagaming5541",
   "text": "don't no",
   "country": null
  },
  {
   "t_offset": 1505.76,
   "external_id": "yt_ChwKGkNKcUx1ZHJodnBVREZhWEw1d01kYUlJaVRn",
   "source": "youtube",
   "author": "@DebashishDibakarBordoloi",
   "text": "it's fake bro",
   "country": null
  },
  {
   "t_offset": 1549.1,
   "external_id": "yt_ChwKGkNMM2prT19odnBVREZUelF3Z1FkZ0E0bjNn",
   "source": "youtube",
   "author": "@HBTYHT",
   "text": "FIFA WORLD CUP LIVE👉 𝐄𝐒𝐏𝐍𝐓𝐕𝐒,𝐂𝐎̷𝐌 :face-blue-wide-eyes::face-blue-wide-eyes:",
   "country": null
  },
  {
   "t_offset": 1549.48,
   "external_id": "yt_ChwKGkNPakVwT19odnBVREZSdmw1d01kb0VvVnRB",
   "source": "youtube",
   "author": "@HBTYHT",
   "text": "FIFA WORLD CUP LIVE👉 𝐄𝐒𝐏𝐍𝐓𝐕𝐒,𝐂𝐎̷𝐌 :face-blue-wide-eyes::face-blue-wide-eyes:",
   "country": null
  },
  {
   "t_offset": 1549.75,
   "external_id": "yt_ChwKGkNOV1N0LV9odnBVREZidmU1d01kdE1VanZR",
   "source": "youtube",
   "author": "@HBTYHT",
   "text": "FIFA WORLD CUP LIVE👉 𝐄𝐒𝐏𝐍𝐓𝐕𝐒,𝐂𝐎̷𝐌 :face-blue-wide-eyes::face-blue-wide-eyes:",
   "country": null
  },
  {
   "t_offset": 1550.06,
   "external_id": "yt_ChwKGkNJejB5ZV9odnBVREZid1RyUVlkSmdrSHl3",
   "source": "youtube",
   "author": "@HBTYHT",
   "text": "FIFA WORLD CUP LIVE👉 𝐄𝐒𝐏𝐍𝐓𝐕𝐒,𝐂𝐎̷𝐌 :face-blue-wide-eyes::face-blue-wide-eyes:",
   "country": null
  },
  {
   "t_offset": 1550.41,
   "external_id": "yt_ChwKGkNOSHkzZV9odnBVREZTc2NkZ1lkTFU4ZmtB",
   "source": "youtube",
   "author": "@HBTYHT",
   "text": "FIFA WORLD CUP LIVE👉 𝐄𝐒𝐏𝐍𝐓𝐕𝐒,𝐂𝐎̷𝐌 :face-blue-wide-eyes::face-blue-wide-eyes:",
   "country": null
  },
  {
   "t_offset": 1550.67,
   "external_id": "yt_ChwKGkNJYlY4ZV9odnBVREZlTFN3Z1Fka0VVUjNR",
   "source": "youtube",
   "author": "@HBTYHT",
   "text": "FIFA WORLD CUP LIVE👉 𝐄𝐒𝐏𝐍𝐓𝐕𝐒,𝐂𝐎̷𝐌 :face-blue-wide-eyes::face-blue-wide-eyes:",
   "country": null
  },
  {
   "t_offset": 1551.0,
   "external_id": "yt_ChwKGkNPQ1ZoZkRodnBVREZUakJ3Z1Fkd093dEN3",
   "source": "youtube",
   "author": "@HBTYHT",
   "text": "FIFA WORLD CUP LIVE👉 𝐄𝐒𝐏𝐍𝐓𝐕𝐒,𝐂𝐎̷𝐌 :face-blue-wide-eyes::face-blue-wide-eyes:",
   "country": null
  },
  {
   "t_offset": 1551.37,
   "external_id": "yt_ChwKGkNPeUxuUERodnBVREZkQV9yUVlkM2RZdktR",
   "source": "youtube",
   "author": "@HBTYHT",
   "text": "FIFA WORLD CUP LIVE👉 𝐄𝐒𝐏𝐍𝐓𝐕𝐒,𝐂𝐎̷𝐌 :face-blue-wide-eyes::face-blue-wide-eyes:",
   "country": null
  },
  {
   "t_offset": 1601.09,
   "external_id": "yt_ChwKGkNNWG4tWWZpdnBVREZXelM0d2NkdjhJTVFn",
   "source": "youtube",
   "author": "@fayonamorgan2062",
   "text": "let's goooooo",
   "country": null
  },
  {
   "t_offset": 1619.01,
   "external_id": "yt_ChwKGkNPbUV1NURpdnBVREZlRFo1d01kWlA0cnZn",
   "source": "youtube",
   "author": "@Sajeena-n2p",
   "text": "eppa thudaghum",
   "country": null
  },
  {
   "t_offset": 1627.04,
   "external_id": "yt_ChwKGkNOM0VwSlRpdnBVREZTSWhkZ1lkUVl3cVhR",
   "source": "youtube",
   "author": "@hindu2135",
   "text": "kitne baje match chalu hoga",
   "country": null
  },
  {
   "t_offset": 1651.09,
   "external_id": "yt_ChwKGkNJLWQ0Sl9pdnBVREZhenp3Z1FkRTZzVTRn",
   "source": "youtube",
   "author": "@Sajeena-n2p",
   "text": "ith real aanoo",
   "country": null
  },
  {
   "t_offset": 1657.42,
   "external_id": "yt_ChwKGkNQYkI1S0xpdnBVREZVckY1d01kZXdRY1VR",
   "source": "youtube",
   "author": "@KROMIK_XP",
   "text": "1baja chalu hoga",
   "country": null
  },
  {
   "t_offset": 1681.79,
   "external_id": "yt_ChwKGkNQZXBzcTdpdnBVREZUbkN3Z1Fkd3VBTDRB",
   "source": "youtube",
   "author": "@Sajeena-n2p",
   "text": "malayaali",
   "country": null
  },
  {
   "t_offset": 1694.68,
   "external_id": "yt_ChwKGkNJU2N5YlRpdnBVREZlUkxxd0lkcXhzTWlB",
   "source": "youtube",
   "author": "@puttaanpulla7539",
   "text": "when does it start",
   "country": null
  },
  {
   "t_offset": 1703.06,
   "external_id": "yt_ChwKGkNLemJ3N2ppdnBVREZjSEd3Z1FkMGUwV2Fn",
   "source": "youtube",
   "author": "@HBTYHT",
   "text": "FIFA WORLD CUP LIVE👉 𝐄𝐒𝐏𝐍𝐓𝐕𝐒,𝐂𝐎̷𝐌 :dothefive::dothefive::dothefive:",
   "country": null
  },
  {
   "t_offset": 1703.23,
   "external_id": "yt_ChwKGkNKT3QwYmppdnBVREZSX0N3Z1FkSnUwMzNn",
   "source": "youtube",
   "author": "@HBTYHT",
   "text": "FIFA WORLD CUP LIVE👉 𝐄𝐒𝐏𝐍𝐓𝐕𝐒,𝐂𝐎̷𝐌 :dothefive::dothefive::dothefive:",
   "country": null
  },
  {
   "t_offset": 1703.39,
   "external_id": "yt_ChwKGkNKN2YyN2ppdnBVREZmSEV3Z1FkU1FVeWFB",
   "source": "youtube",
   "author": "@HBTYHT",
   "text": "FIFA WORLD CUP LIVE👉 𝐄𝐒𝐏𝐍𝐓𝐕𝐒,𝐂𝐎̷𝐌 :dothefive::dothefive::dothefive:",
   "country": null
  },
  {
   "t_offset": 1703.73,
   "external_id": "yt_ChwKGkNOclY3YmppdnBVREZUb296QVFkYktRMXZR",
   "source": "youtube",
   "author": "@HBTYHT",
   "text": "FIFA WORLD CUP LIVE👉 𝐄𝐒𝐏𝐍𝐓𝐕𝐒,𝐂𝐎̷𝐌 :dothefive::dothefive::dothefive:",
   "country": null
  },
  {
   "t_offset": 1704.07,
   "external_id": "yt_ChwKGkNQajZnYm5pdnBVREZjN0x3Z1FkRFFJZ0xB",
   "source": "youtube",
   "author": "@HBTYHT",
   "text": "FIFA WORLD CUP LIVE👉 𝐄𝐒𝐏𝐍𝐓𝐕𝐒,𝐂𝐎̷𝐌 :dothefive::dothefive::dothefive:",
   "country": null
  },
  {
   "t_offset": 1704.37,
   "external_id": "yt_ChwKGkNQVGlscm5pdnBVREZUTFM1d01kUHlzckh3",
   "source": "youtube",
   "author": "@HBTYHT",
   "text": "FIFA WORLD CUP LIVE👉 𝐄𝐒𝐏𝐍𝐓𝐕𝐒,𝐂𝐎̷𝐌 :dothefive::dothefive::dothefive:",
   "country": null
  },
  {
   "t_offset": 1704.67,
   "external_id": "yt_ChwKGkNKN0dwN25pdnBVREZUelR3Z1FkT2I0c293",
   "source": "youtube",
   "author": "@HBTYHT",
   "text": "FIFA WORLD CUP LIVE👉 𝐄𝐒𝐏𝐍𝐓𝐕𝐒,𝐂𝐎̷𝐌 :dothefive::dothefive::dothefive:",
   "country": null
  },
  {
   "t_offset": 1705.07,
   "external_id": "yt_ChwKGkNKM0F2N25pdnBVREZRQVRyUVlkVjlBczN3",
   "source": "youtube",
   "author": "@HBTYHT",
   "text": "FIFA WORLD CUP LIVE👉 𝐄𝐒𝐏𝐍𝐓𝐕𝐒,𝐂𝐎̷𝐌 :dothefive::dothefive::dothefive:",
   "country": null
  },
  {
   "t_offset": 1710.22,
   "external_id": "yt_ChwKGkNPckUtYnZpdnBVREZaREl3Z1FkT29FZFRR",
   "source": "youtube",
   "author": "@CASTLE_VANIA",
   "text": "this fake live 🙂 match already started",
   "country": null
  },
  {
   "t_offset": 1734.56,
   "external_id": "yt_ChwKGkNOell5Y2ZpdnBVREZlN0R3Z1FkalpNM1FR",
   "source": "youtube",
   "author": "@Sajeena-n2p",
   "text": "searisly😔",
   "country": null
  },
  {
   "t_offset": 1741.82,
   "external_id": "yt_ChwKGkNObmZnc3ZpdnBVREZlTFB3Z1FkUHNROTRR",
   "source": "youtube",
   "author": "@CASTLE_VANIA",
   "text": "yess",
   "country": null
  },
  {
   "t_offset": 1772.83,
   "external_id": "yt_ChwKGkNOT0U1OW5pdnBVREZmakc1d01kbnVzU0dB",
   "source": "youtube",
   "author": "@Sajeena-n2p",
   "text": "mach kaanunnath aethil aamn",
   "country": null
  },
  {
   "t_offset": 1849.45,
   "external_id": "yt_ChwKGkNMTDVxXzdpdnBVREZVWER3Z1FkNEdnNG93",
   "source": "youtube",
   "author": "@HBTYHT",
   "text": "FIFA WORLD CUP LIVE👉 𝐄𝐒𝐏𝐍𝐓𝐕𝐒,𝐂𝐎̷𝐌 :face-blue-wide-eyes::face-blue-wide-eyes:",
   "country": null
  },
  {
   "t_offset": 1849.75,
   "external_id": "yt_ChwKGkNNLTV2djdpdnBVREZSYkx3Z1FkcTFNdVd3",
   "source": "youtube",
   "author": "@HBTYHT",
   "text": "FIFA WORLD CUP LIVE👉 𝐄𝐒𝐏𝐍𝐓𝐕𝐒,𝐂𝐎̷𝐌 :face-blue-wide-eyes::face-blue-wide-eyes:",
   "country": null
  },
  {
   "t_offset": 1850.06,
   "external_id": "yt_ChwKGkNKM1p6XzdpdnBVREZiOE5kZ1lkaWtjdl9n",
   "source": "youtube",
   "author": "@HBTYHT",
   "text": "FIFA WORLD CUP LIVE👉 𝐄𝐒𝐏𝐍𝐓𝐕𝐒,𝐂𝐎̷𝐌 :face-blue-wide-eyes::face-blue-wide-eyes:",
   "country": null
  },
  {
   "t_offset": 1850.32,
   "external_id": "yt_ChwKGkNPLTg0XzdpdnBVREZlTFB3Z1FkUHNROTRR",
   "source": "youtube",
   "author": "@HBTYHT",
   "text": "FIFA WORLD CUP LIVE👉 𝐄𝐒𝐏𝐍𝐓𝐕𝐒,𝐂𝐎̷𝐌 :face-blue-wide-eyes::face-blue-wide-eyes:",
   "country": null
  },
  {
   "t_offset": 1850.64,
   "external_id": "yt_ChwKGkNKbnU5djdpdnBVREZZZkV3Z1FkeVV3OHBB",
   "source": "youtube",
   "author": "@HBTYHT",
   "text": "FIFA WORLD CUP LIVE👉 𝐄𝐒𝐏𝐍𝐓𝐕𝐒,𝐂𝐎̷𝐌 :face-blue-wide-eyes::face-blue-wide-eyes:",
   "country": null
  },
  {
   "t_offset": 1851.03,
   "external_id": "yt_ChwKGkNKSGhpX19pdnBVREZSNFZkZ1lkYWFZUHpB",
   "source": "youtube",
   "author": "@HBTYHT",
   "text": "FIFA WORLD CUP LIVE👉 𝐄𝐒𝐏𝐍𝐓𝐕𝐒,𝐂𝐎̷𝐌 :face-blue-wide-eyes::face-blue-wide-eyes:",
   "country": null
  },
  {
   "t_offset": 1851.3,
   "external_id": "yt_ChwKGkNMSHluZl9pdnBVREZlTGV3Z1FkZ000ME1n",
   "source": "youtube",
   "author": "@HBTYHT",
   "text": "FIFA WORLD CUP LIVE👉 𝐄𝐒𝐏𝐍𝐓𝐕𝐒,𝐂𝐎̷𝐌 :face-blue-wide-eyes::face-blue-wide-eyes:",
   "country": null
  },
  {
   "t_offset": 1851.66,
   "external_id": "yt_ChwKGkNQYTNzdl9pdnBVREZVYkR3Z1FkQ1ZFNTVB",
   "source": "youtube",
   "author": "@HBTYHT",
   "text": "FIFA WORLD CUP LIVE👉 𝐄𝐒𝐏𝐍𝐓𝐕𝐒,𝐂𝐎̷𝐌 :face-blue-wide-eyes::face-blue-wide-eyes:",
   "country": null
  },
  {
   "t_offset": 1900.39,
   "external_id": "yt_ChwKGkNOUDIxSmJqdnBVREZTa29kZ1lkSkU4N2tn",
   "source": "youtube",
   "author": "@NischalMagar-fg8xq",
   "text": "🤡",
   "country": null
  },
  {
   "t_offset": 1946.07,
   "external_id": "yt_ChwKGkNJejR0YXpqdnBVREZmZ1lyUVlkVVFBazVn",
   "source": "youtube",
   "author": "@Jostrajosua",
   "text": "nonton apaan ini",
   "country": null
  },
  {
   "t_offset": 1952.63,
   "external_id": "yt_ChwKGkNKSzh5cV9qdnBVREZUX0N3Z1FkajBzcGlR",
   "source": "youtube",
   "author": "@Jostrajosua",
   "text": "gajelas amat",
   "country": null
  },
  {
   "t_offset": 1998.15,
   "external_id": "yt_ChwKGkNQbmdvc1hqdnBVREZlM2p3Z1FkdF9ZUGJR",
   "source": "youtube",
   "author": "@dhavalbhinde4336",
   "text": "is this real or fake???",
   "country": null
  },
  {
   "t_offset": 2130.05,
   "external_id": "yt_ChwKGkNJempsb1RrdnBVREZiVEQ1d01kRTFvYVl3",
   "source": "youtube",
   "author": "@LokeshDarwatkar-q4b",
   "text": "fake",
   "country": null
  },
  {
   "t_offset": 2417.22,
   "external_id": "yt_ChwKGkNMSFpqbzNsdnBVREZZbzZkZ1lkUlJnUlhn",
   "source": "youtube",
   "author": "@SangamKumar-k2d",
   "text": "ronaloooo",
   "country": null
  },
  {
   "t_offset": 2547.0,
   "external_id": "yt_ChwKGkNKLUtfc3JsdnBVREZYTEV3Z1FkM3pNclJB",
   "source": "youtube",
   "author": "@ft.oml-09",
   "text": "how see the game",
   "country": null
  },
  {
   "t_offset": 2575.31,
   "external_id": "yt_ChwKGkNKYTN3TmpsdnBVREZadmV3Z1FkTDM0Q0Fn",
   "source": "youtube",
   "author": "@TikTok-q6f8t",
   "text": "show the match",
   "country": null
  },
  {
   "t_offset": 2604.94,
   "external_id": "yt_ChwKGkNLWFh6dWJsdnBVREZjSEJ3Z1FkUmZRM3pn",
   "source": "youtube",
   "author": "@Azhak222",
   "text": "cr7🦅",
   "country": null
  },
  {
   "t_offset": 2640.84,
   "external_id": "yt_ChwKGkNPYlE0dmZsdnBVREZXbHRxd0lkNjhnRzZR",
   "source": "youtube",
   "author": "@StinkyJoe67",
   "text": "noooo sonaldo rex 😢",
   "country": null
  },
  {
   "t_offset": 2658.64,
   "external_id": "yt_ChwKGkNOTzhvSURtdnBVREZZMHQxZ0FkRUFBQzZR",
   "source": "youtube",
   "author": "@Khanii123-c8l7i",
   "text": "cr7",
   "country": null
  },
  {
   "t_offset": 2734.53,
   "external_id": "yt_ChwKGkNLenJ0YVRtdnBVREZSNF9yUVlkR1N3ODZB",
   "source": "youtube",
   "author": "@rajen275",
   "text": "cr7",
   "country": null
  },
  {
   "t_offset": 2766.36,
   "external_id": "yt_ChwKGkNJdW56TFBtdnBVREZlN0R3Z1FkalpNM1FR",
   "source": "youtube",
   "author": "@AQUAUMP",
   "text": "cr7",
   "country": null
  },
  {
   "t_offset": 2787.82,
   "external_id": "yt_ChwKGkNLZm82NzNtdnBVREZZbzZkZ1lkUlJnUlhn",
   "source": "youtube",
   "author": "@heyyshxdy",
   "text": "/cam 2",
   "country": null
  },
  {
   "t_offset": 2809.94,
   "external_id": "yt_ChwKGkNOaTNzTWptdnBVREZUbkN3Z1Fkd3VBTDRB",
   "source": "youtube",
   "author": "@Robloxian-c6k",
   "text": "woe",
   "country": null
  },
  {
   "t_offset": 2812.23,
   "external_id": "yt_ChwKGkNOMkF2Y25tdnBVREZZZkV3Z1FkeVV3OHBB",
   "source": "youtube",
   "author": "@Dhruva.M-i9j",
   "text": "is it real or fake",
   "country": null
  },
  {
   "t_offset": 2843.89,
   "external_id": "yt_ChwKGkNPR3h6dGptdnBVREZRM0hQd1FkNHhRaVdn",
   "source": "youtube",
   "author": "@shainytorres6475",
   "text": "ᴄʀ7",
   "country": null
  },
  {
   "t_offset": 2876.98,
   "external_id": "yt_ChwKGkNMS1FxLWptdnBVREZaWEh3Z1FkaURjVFFn",
   "source": "youtube",
   "author": "@keshabkc8967",
   "text": "app bata kasari herne",
   "country": null
  },
  {
   "t_offset": 2887.83,
   "external_id": "yt_ChwKGkNJU2h3ZTNtdnBVREZaVGZ3Z1FkaVBBTzFn",
   "source": "youtube",
   "author": "@SaharukKhan-es2lf",
   "text": "cr7 2goal geranty",
   "country": null
  },
  {
   "t_offset": 2897.82,
   "external_id": "yt_ChwKGkNOV1pvX0xtdnBVREZhekNMUUFkeFNJNGN3",
   "source": "youtube",
   "author": "@Robloxian-c6k",
   "text": "wsp",
   "country": null
  },
  {
   "t_offset": 2899.72,
   "external_id": "yt_ChwKGkNKZl9sX1BtdnBVREZZbE1UQWdkZVk4dW1B",
   "source": "youtube",
   "author": "@Robloxian-c6k",
   "text": "wsp",
   "country": null
  },
  {
   "t_offset": 2901.32,
   "external_id": "yt_ChwKGkNQRGMtUFBtdnBVREZjdDZUQWdkQ0gwdGRR",
   "source": "youtube",
   "author": "@Robloxian-c6k",
   "text": "wsp",
   "country": null
  },
  {
   "t_offset": 2903.07,
   "external_id": "yt_ChwKGkNLQzY1dlRtdnBVREZSN0RMUUFkX0xBa1FB",
   "source": "youtube",
   "author": "@Robloxian-c6k",
   "text": "wsp",
   "country": null
  },
  {
   "t_offset": 2905.14,
   "external_id": "yt_ChwKGkNQalk0dlhtdnBVREZVQnRUQWdkUFI4Sm5B",
   "source": "youtube",
   "author": "@Robloxian-c6k",
   "text": "wsp",
   "country": null
  },
  {
   "t_offset": 2905.91,
   "external_id": "yt_ChwKGkNPcl9rdmJtdnBVREZlcE1UQWdkcnlnNk93",
   "source": "youtube",
   "author": "@RAJ_LIVE-p7b",
   "text": "I think loop video",
   "country": null
  },
  {
   "t_offset": 2906.44,
   "external_id": "yt_ChwKGkNPZmxzZmJtdnBVREZjejB3Z1FkWTZNTGdR",
   "source": "youtube",
   "author": "@Robloxian-c6k",
   "text": "wsp",
   "country": null
  },
  {
   "t_offset": 2907.09,
   "external_id": "yt_ChwKGkNMM2gyZmJtdnBVREZjSEd3Z1FkMGUwV2Fn",
   "source": "youtube",
   "author": "@keshabkc8967",
   "text": "app bata free ma kasari herne",
   "country": null
  },
  {
   "t_offset": 2907.7,
   "external_id": "yt_ChwKGkNOblFnUGZtdnBVREZlTjhUQWdkcjBNMDRR",
   "source": "youtube",
   "author": "@Robloxian-c6k",
   "text": "wsp",
   "country": null
  },
  {
   "t_offset": 2945.32,
   "external_id": "yt_ChwKGkNKdVg5b2pudnBVREZkdzZkZ1lkeEFZMnNR",
   "source": "youtube",
   "author": "@RAJ_LIVE-p7b",
   "text": "fake video",
   "country": null
  },
  {
   "t_offset": 3160.35,
   "external_id": "yt_ChwKGkNJLVd2T19udnBVREZYN0l3Z1FkU21NZ0pR",
   "source": "youtube",
   "author": "@ShantomoniShantomomi",
   "text": "onlly on cr7",
   "country": null
  },
  {
   "t_offset": 3176.07,
   "external_id": "yt_ChwKGkNNZU5fUGJudnBVREZiN0h3Z1FkZVVvS1Fn",
   "source": "youtube",
   "author": "@ShantomoniShantomomi",
   "text": "onlly on cr7",
   "country": null
  },
  {
   "t_offset": 3190.16,
   "external_id": "yt_ChwKGkNOejIyZjNudnBVREZTREJ3Z1Fkc3pNQ0FR",
   "source": "youtube",
   "author": "@prakashsunar7416",
   "text": "portugal 🇵🇹🇵🇹🇵🇹🇵🇹🇵🇹🇵🇹🇵🇹🇵🇹🇵🇹🇵🇹🇵🇹🇵🇹🇵🇹🇵🇹🇵🇹🇵🇹🇵🇹🇵🇹🇵🇹🇵🇹🇵🇹🇵🇹🇵🇹🇵🇹🇵🇹🇵🇹🇵🇹🇵🇹🇵🇹🇵🇹🇵🇹🇵🇹🇵🇹🇵🇹🇵🇹🇵🇹🇵🇹🇵🇹🇵🇹🇵🇹🇵🇹🇵🇹🇵🇹🇵🇹🇵🇹🇵🇹🇵🇹🇵🇹🇵🇹🇵🇹🇵🇹🇵🇹🇵🇹🇵🇹🇵🇹🇵🇹🇵🇹🇵🇹🇵🇹🇵🇹🇵🇹🇵🇹🇵🇹🇵🇹🇵🇹🇵🇹🇵🇹🇵🇹🇵🇹🇵🇹🇵🇹🇵🇹🇵🇹🇵🇹🇵🇹🇵🇹",
   "country": null
  },
  {
   "t_offset": 3234.37,
   "external_id": "yt_ChwKGkNLQ2w1SkxvdnBVREZZZkV3Z1FkeVV3OHBB",
   "source": "youtube",
   "author": "@matthew-l3g8e",
   "text": "h\\i",
   "country": null
  },
  {
   "t_offset": 3300.48,
   "external_id": "yt_ChwKGkNNX1hwN0xvdnBVREZlN0R3Z1FkalpNM1FR",
   "source": "youtube",
   "author": "@YuwarajSinghdadal",
   "text": "Portugal",
   "country": null
  },
  {
   "t_offset": 3501.78,
   "external_id": "yt_ChwKGkNOQ2dwSkxwdnBVREZmZkI1d01kN08wd1Bn",
   "source": "youtube",
   "author": "@asrar_72",
   "text": "fake h ya réal h",
   "country": null
  },
  {
   "t_offset": 3507.18,
   "external_id": "yt_ChwKGkNLLTM4WlRwdnBVREZURFF3Z1FkTTNJeGl3",
   "source": "youtube",
   "author": "@demistankalep9427",
   "text": "Suiiiiiiiiiii",
   "country": null
  },
  {
   "t_offset": 3518.57,
   "external_id": "yt_ChwKGkNQbkpwWnJwdnBVREZVWER3Z1FkbzNzNC1B",
   "source": "youtube",
   "author": "@demistankalep9427",
   "text": "Suiiiiiiiii",
   "country": null
  },
  {
   "t_offset": 3530.7,
   "external_id": "yt_ChwKGkNNYlppYURwdnBVREZmZkI1d01kN08wd1Bn",
   "source": "youtube",
   "author": "@demistankalep9427",
   "text": "CR7",
   "country": null
  },
  {
   "t_offset": 3542.55,
   "external_id": "yt_ChwKGkNQeWIzS1hwdnBVREZlamZ3Z1FkZVRBQmFB",
   "source": "youtube",
   "author": "@demistankalep9427",
   "text": "🇵🇹🇵🇹🇵🇹🇵🇹🇵🇹🇵🇹🇵🇹🇵🇹🇵🇹🇵🇹🇵🇹",
   "country": null
  },
  {
   "t_offset": 3550.14,
   "external_id": "yt_ChwKGkNQWHNxNm5wdnBVREZTam81d01kcGZjMzFB",
   "source": "youtube",
   "author": "@PongtaiAtai",
   "text": "r they playing now",
   "country": null
  },
  {
   "t_offset": 3552.81,
   "external_id": "yt_ChwKGkNPSDV6NnJwdnBVREZkdzZkZ1lkeEFZMnNR",
   "source": "youtube",
   "author": "@demistankalep9427",
   "text": "Suiiiiiiiiiiiiiiiiiiiiiiiiiiiiiiiiii",
   "country": null
  },
  {
   "t_offset": 3564.71,
   "external_id": "yt_ChwKGkNQT2lxTERwdnBVREZWb19yUVlkNHZvdERB",
   "source": "youtube",
   "author": "@tanishjeengar9535",
   "text": "when will the match start",
   "country": null
  },
  {
   "t_offset": 3568.67,
   "external_id": "yt_ChwKGkNNcndtckxwdnBVREZjdDZUQWdkQ0gwdGRR",
   "source": "youtube",
   "author": "@tanishjeengar9535",
   "text": "when will the match start",
   "country": null
  },
  {
   "t_offset": 3573.1,
   "external_id": "yt_ChwKGkNJekFwYlRwdnBVREZmZ1lyUVlkVVFBazVn",
   "source": "youtube",
   "author": "@tanishjeengar9535",
   "text": "when will the match start",
   "country": null
  },
  {
   "t_offset": 3575.94,
   "external_id": "yt_ChwKGkNQMmYxTFhwdnBVREZUb296QVFkYktRMXZR",
   "source": "youtube",
   "author": "@demistankalep9427",
   "text": "Suiiiiiiiiiii",
   "country": null
  },
  {
   "t_offset": 3579.15,
   "external_id": "yt_ChwKGkNKS0dtN2ZwdnBVREZUX0N3Z1FkajBzcGlR",
   "source": "youtube",
   "author": "@tanishjeengar9535",
   "text": "when will the match start",
   "country": null
  },
  {
   "t_offset": 3586.24,
   "external_id": "yt_ChwKGkNPWFp6YnJwdnBVREZWZ3FyUVlkaDhVbW93",
   "source": "youtube",
   "author": "@tanishjeengar9535",
   "text": "when will the match start",
   "country": null
  },
  {
   "t_offset": 3591.88,
   "external_id": "yt_ChwKGkNQRDJvTDNwdnBVREZjVGc1d01kUU5jWldR",
   "source": "youtube",
   "author": "@tanishjeengar9535",
   "text": "when will the match start",
   "country": null
  },
  {
   "t_offset": 3596.92,
   "external_id": "yt_ChwKGkNMSFQxN19wdnBVREZjMHl6QVFkQ2RvM0tR",
   "source": "youtube",
   "author": "@PongtaiAtai",
   "text": "3 am",
   "country": null
  },
  {
   "t_offset": 3602.27,
   "external_id": "yt_ChwKGkNKX3ZtOExwdnBVREZWUk9UQWdkcGR3aTVB",
   "source": "youtube",
   "author": "@tanishjeengar9535",
   "text": "when will the match start",
   "country": null
  },
  {
   "t_offset": 3608.24,
   "external_id": "yt_ChwKGkNOcXloOFhwdnBVREZid1RyUVlkSmdrSHl3",
   "source": "youtube",
   "author": "@tanishjeengar9535",
   "text": "okk",
   "country": null
  },
  {
   "t_offset": 3683.44,
   "external_id": "yt_ChwKGkNOS1UtT2pwdnBVREZmZ1lyUVlkVVFBazVn",
   "source": "youtube",
   "author": "@PongtaiAtai",
   "text": "it was in 12:30 am but why its not start",
   "country": null
  },
  {
   "t_offset": 3684.63,
   "external_id": "yt_ChwKGkNKYlJ2ZW5wdnBVREZid1RyUVlkSmdrSHl3",
   "source": "youtube",
   "author": "@SureshSingMura-tr1nd",
   "text": "Siuuuuuuuu",
   "country": null
  },
  {
   "t_offset": 3747.11,
   "external_id": "yt_ChwKGkNJSzFwSWZxdnBVREZYalk1d01kdFZZeDhR",
   "source": "youtube",
   "author": "@tanishjeengar9535",
   "text": "you said 3 am do you even know?",
   "country": null
  },
  {
   "t_offset": 3782.83,
   "external_id": "yt_ChwKGkNNVFdxWmpxdnBVREZkWldFZ0VkYWdFMkFB",
   "source": "youtube",
   "author": "@StephanieLoya-n7j",
   "text": "Im leaving the live if you don’t show proof it isnt started",
   "country": null
  },
  {
   "t_offset": 3787.79,
   "external_id": "yt_ChwKGkNQaUkxWnJxdnBVREZiWHk1d01kMEFBR3Bn",
   "source": "youtube",
   "author": "@ayushharijan-h9l7c",
   "text": "match was started",
   "country": null
  },
  {
   "t_offset": 3799.94,
   "external_id": "yt_ChwKGkNPV092cURxdnBVREZaRUhGUVVkX0hnTW1B",
   "source": "youtube",
   "author": "@StephanieLoya-n7j",
   "text": "Oh",
   "country": null
  },
  {
   "t_offset": 3822.49,
   "external_id": "yt_ChwKGkNOdXNuS3ZxdnBVREZkUE81d01kSW5nZ1d3",
   "source": "youtube",
   "author": "@GATIRTHA",
   "text": "si",
   "country": null
  },
  {
   "t_offset": 3830.39,
   "external_id": "yt_ChwKGkNLelRnS19xdnBVREZmakc1d01kbnVzU0dB",
   "source": "youtube",
   "author": "@demistankalep9427",
   "text": "Suiiiiiiiii",
   "country": null
  },
  {
   "t_offset": 3905.69,
   "external_id": "yt_ChwKGkNPX1Q5ZExxdnBVREZmclF3Z1FkSGRBUGhB",
   "source": "youtube",
   "author": "@GATIRTHA",
   "text": "game start no but why",
   "country": null
  },
  {
   "t_offset": 3922.08,
   "external_id": "yt_ChwKGkNKNmMzZHJxdnBVREZYalk1d01kdFZZeDhR",
   "source": "youtube",
   "author": "@AradhikasVlog",
   "text": "Game start?",
   "country": null
  },
  {
   "t_offset": 3935.88,
   "external_id": "yt_ChwKGkNLXzZwZUhxdnBVREZhWEw1d01kYUlJaVRn",
   "source": "youtube",
   "author": "@KaustubhTiwari-30",
   "text": "Fahhhh",
   "country": null
  },
  {
   "t_offset": 3976.86,
   "external_id": "yt_ChwKGkNOTF83dlRxdnBVREZlTGV3Z1FkZ000ME1n",
   "source": "youtube",
   "author": "@KaustubhTiwari-30",
   "text": "Massi . Hsheuhsusheve hzhz",
   "country": null
  },
  {
   "t_offset": 4025.66,
   "external_id": "yt_ChwKGkNKVGZrSXpydnBVREZVX0U1d01kZnVBTm1n",
   "source": "youtube",
   "author": "@KaustubhTiwari-30",
   "text": "All fifa is loss",
   "country": null
  },
  {
   "t_offset": 4026.82,
   "external_id": "yt_ChwKGkNNYksySXpydnBVREZSNDB6QVFkYlI4WTln",
   "source": "youtube",
   "author": "@GATIRTHA",
   "text": "jhatta start gara la Nana u",
   "country": null
  },
  {
   "t_offset": 4028.98,
   "external_id": "yt_ChwKGkNNcUEzWTNydnBVREZVckY1d01kZXdRY1VR",
   "source": "youtube",
   "author": "@vikashrabha9634",
   "text": "game dikhado channel walo",
   "country": null
  },
  {
   "t_offset": 4070.19,
   "external_id": "yt_ChwKGkNJRFBxcUhydnBVREZkZkF3Z1FkUE1RS293",
   "source": "youtube",
   "author": "@GATIRTHA",
   "text": ":face-orange-frowning:",
   "country": null
  },
  {
   "t_offset": 4173.79,
   "external_id": "yt_ChwKGkNQREwzdExydnBVREZibC1UQWdkdF9vdVVn",
   "source": "youtube",
   "author": "@sameermarne6281",
   "text": "What time will be game started ?",
   "country": null
  },
  {
   "t_offset": 4238.72,
   "external_id": "yt_ChwKGkNOQ0cyX0hydnBVREZiN0h3Z1FkZVVvS1Fn",
   "source": "youtube",
   "author": "@Sahu__1",
   "text": "china arunachal pradesh k border tak aagya hai or ye game dekha raha hai...ye hai godi media",
   "country": null
  },
  {
   "t_offset": 4469.91,
   "external_id": "yt_ChwKGkNPTFEtTl9zdnBVREZXd3NkZ1lkOUljOGt3",
   "source": "youtube",
   "author": "@YouTubeojk",
   "text": "suiiiiiiiiiiiiiiiiii",
   "country": null
  },
  {
   "t_offset": 4746.75,
   "external_id": "yt_ChwKGkNOVEhfLVB0dnBVREZlc0dkZ1lkeUU0dWRn",
   "source": "youtube",
   "author": "@JignaBhatt-y6h",
   "text": "bro hi",
   "country": null
  },
  {
   "t_offset": 4752.24,
   "external_id": "yt_ChwKGkNKXzF6ZWJ0dnBVREZUbkN3Z1Fkd3VBTDRB",
   "source": "youtube",
   "author": "@RabindranathBag-b6p",
   "text": "baler live🤬",
   "country": null
  },
  {
   "t_offset": 4765.98,
   "external_id": "yt_ChwKGkNPelZrdTN0dnBVREZjamw1d01kc0E4bVZB",
   "source": "youtube",
   "author": "@time-u1j",
   "text": "shuuuuuuuuuu",
   "country": null
  },
  {
   "t_offset": 5229.71,
   "external_id": "yt_ChwKGkNMdmtxY3J2dnBVREZjNU5xd0lkdWo4bElB",
   "source": "youtube",
   "author": "@Masaabfayaz99",
   "text": "Bro show us match",
   "country": null
  },
  {
   "t_offset": 5240.21,
   "external_id": "yt_ChwKGkNOcVNxTV92dnBVREZXOEoxZ0FkS2lFY2xB",
   "source": "youtube",
   "author": "@hodweekzak",
   "text": "did it start",
   "country": null
  },
  {
   "t_offset": 5261.08,
   "external_id": "yt_ChwKGkNJNlRudG52dnBVREZSX0N3Z1FkSnUwMzNn",
   "source": "youtube",
   "author": "@SamShady-t3v8d",
   "text": "bro show match",
   "country": null
  },
  {
   "t_offset": 5263.07,
   "external_id": "yt_ChwKGkNPZkxtZHJ2dnBVREZVVGV3Z1Fkb3JJeGx3",
   "source": "youtube",
   "author": "@BhatBisma-h8y7p",
   "text": "aary match dekhWona",
   "country": null
  },
  {
   "t_offset": 5284.88,
   "external_id": "yt_ChwKGkNNYkx6dVR2dnBVREZlN0R3Z1FkalpNM1FR",
   "source": "youtube",
   "author": "@SamShady-t3v8d",
   "text": "match ni dikharaha mdcht",
   "country": null
  },
  {
   "t_offset": 5438.55,
   "external_id": "yt_ChwKGkNPUHQ3cTN3dnBVREZVdzRkZ1lka2lZRlhB",
   "source": "youtube",
   "author": "@Tgrthakurgaming",
   "text": "kya kar Raha hai bhai ronaldo ko dikha",
   "country": null
  },
  {
   "t_offset": 5579.98,
   "external_id": "yt_ChwKGkNQTDNxUEh3dnBVREZVakR3Z1FkTWxraENR",
   "source": "youtube",
   "author": "@JayataMukherjee",
   "text": "are show us the match....we are not here to watch the spectaculars",
   "country": null
  },
  {
   "t_offset": 5631.67,
   "external_id": "yt_ChwKGkNPX1Atb254dnBVREZlb1RyUVlkYlFJakR3",
   "source": "youtube",
   "author": "@HarishHarish-q2i2p",
   "text": "come on portugal...🫡🫡",
   "country": null
  },
  {
   "t_offset": 5671.44,
   "external_id": "yt_ChwKGkNLNlMtSnp4dnBVREZlTGV3Z1FkZ000ME1n",
   "source": "youtube",
   "author": "@HarishHarish-q2i2p",
   "text": "hey I want to see the match dude",
   "country": null
  },
  {
   "t_offset": 5691.94,
   "external_id": "yt_ChwKGkNJVy0xNmJ4dnBVREZUckN3Z1FkeG1NYlJB",
   "source": "youtube",
   "author": "@LEARNFULLSTACK-v5r",
   "text": "war:face-red-droopy-eyes:",
   "country": null
  },
  {
   "t_offset": 5801.82,
   "external_id": "yt_ChwKGkNJTG1rZHZ4dnBVREZTX3JQd1FkOHhjTVlB",
   "source": "youtube",
   "author": "@TITAN-q6b",
   "text": "halla madrid",
   "country": null
  },
  {
   "t_offset": 6102.38,
   "external_id": "yt_ChwKGkNJM1V1T3J5dnBVREZadmV3Z1FkTDM0Q0Fn",
   "source": "youtube",
   "author": "@aulialarasatiputriAulia",
   "text": "mana ko blm main",
   "country": null
  },
  {
   "t_offset": 6563.61,
   "external_id": "yt_ChwKGkNMbUNzY2IwdnBVREZjejB3Z1FkWTZNTGdR",
   "source": "youtube",
   "author": "@NameLess-fh1oo",
   "text": "this match is so ahh",
   "country": null
  },
  {
   "t_offset": 6597.93,
   "external_id": "yt_ChwKGkNPZjIzTmIwdnBVREZVWEQ1d01kNTg4dVdn",
   "source": "youtube",
   "author": "@Soumyaranjan-k7g",
   "text": "bro match dikha",
   "country": null
  },
  {
   "t_offset": 7541.0,
   "external_id": "yt_ChwKGkNPN2Z1cGo0dnBVREZhYmg1d01kZW1vY3Nn",
   "source": "youtube",
   "author": "@luisa00676",
   "text": "nah bro Ronaldo",
   "country": null
  },
  {
   "t_offset": 7591.24,
   "external_id": "yt_ChwKGkNPcXl0ckQ0dnBVREZVZ2JkZ1lkdEVJVUh3",
   "source": "youtube",
   "author": "@arunkakde528",
   "text": ":hand-pink-waving::text-green-game-over::hand-pink-waving:",
   "country": null
  },
  {
   "t_offset": 7607.73,
   "external_id": "yt_ChwKGkNMdjJvcmo0dnBVREZSNFZkZ1lkYWFZUHpB",
   "source": "youtube",
   "author": "@luisa00676",
   "text": "gg Spain",
   "country": null
  },
  {
   "t_offset": 7757.97,
   "external_id": "yt_ChwKGkNPNkgtZl80dnBVREZYeUh5d0VkU2xrR2pn",
   "source": "youtube",
   "author": "@OliviaCampbell-n2s",
   "text": "show the game",
   "country": null
  },
  {
   "t_offset": 7805.1,
   "external_id": "yt_ChwKGkNPLTB0SmI1dnBVREZidmU1d01kdE1VanZR",
   "source": "youtube",
   "author": "@tocastorylife",
   "text": "lets go SPAINNNNN",
   "country": null
  },
  {
   "t_offset": 7962.68,
   "external_id": "yt_ChwKGkNPcVV5dUg1dnBVREZZOWRxd0lka3lBbm9B",
   "source": "youtube",
   "author": "@Hani-v5q3p",
   "text": "purtugalll",
   "country": null
  },
  {
   "t_offset": 8553.24,
   "external_id": "yt_ChwKGkNNelNrX3Y3dnBVREZjRW5kZ1lkWVg0ZFRn",
   "source": "youtube",
   "author": "@Sementara-j2m",
   "text": "kalk nengok siadan langsung di jala live",
   "country": null
  },
  {
   "t_offset": 9477.56,
   "external_id": "yt_ChwKGkNQclotTFBfdnBVREZlSTR6QVFkQlE4U0x3",
   "source": "youtube",
   "author": "@Bubble_mlbb2a",
   "text": "speed crying inside the car lamao",
   "country": null
  }
 ]
}